tklearn/__init__.py
tklearn/config.py
tklearn/logging.py
tklearn/py.typed
tklearn/scripts.py
tklearn/base/__init__.py
tklearn/base/resource.py
tklearn/kb/__init__.py
tklearn/kb/conceptnet/__init__.py
tklearn/kb/conceptnet/concept.py
tklearn/kb/conceptnet/io.py
tklearn/kb/conceptnet/relation.py
tklearn/kb/conceptnet/uri.py
tklearn/kb/emolex/__init__.py
tklearn/kb/emolex/io.py
tklearn/lang/__init__.py
tklearn/lang/en/__init__.py
tklearn/lang/en/_contractions.py
tklearn/llm/__init__.py
tklearn/llm/constraint.py
tklearn/llm/verbalizer.py
tklearn/metrics/__init__.py
tklearn/metrics/array_accumulator.py
tklearn/metrics/base.py
tklearn/metrics/bias.py
tklearn/metrics/classification.py
tklearn/metrics/generation.py
tklearn/metrics/statistical_tests.py
tklearn/metrics/steps_counter.py
tklearn/models/__init__.py
tklearn/models/base.py
tklearn/models/backbone/__init__.py
tklearn/models/backbone/adapter.py
tklearn/models/backbone/base.py
tklearn/models/backbone/transformer.py
tklearn/models/multiclass/__init__.py
tklearn/models/multiclass/classifier.py
tklearn/models/multiclass/helpers.py
tklearn/nn/__init__.py
tklearn/nn/loss.py
tklearn/nn/optim.py
tklearn/nn/base/__init__.py
tklearn/nn/base/helpers.py
tklearn/nn/base/module.py
tklearn/nn/callbacks/__init__.py
tklearn/nn/callbacks/base.py
tklearn/nn/callbacks/checkpoint.py
tklearn/nn/callbacks/early_stopping.py
tklearn/nn/callbacks/history.py
tklearn/nn/callbacks/plateau_early_stopping.py
tklearn/nn/callbacks/progbar_logger.py
tklearn/nn/callbacks/tracking.py
tklearn/nn/utils/__init__.py
tklearn/nn/utils/collections.py
tklearn/nn/utils/preprocessing.py
tklearn/pipelines/__init__.py
tklearn/pipelines/translate.py
tklearn/preprocessing/__init__.py
tklearn/preprocessing/annotator.py
tklearn/preprocessing/emoticons.py
tklearn/preprocessing/preprocessor.py
tklearn/preprocessing/tokenization.py
tklearn/utils/__init__.py
tklearn/utils/array.py
tklearn/utils/copy.py
tklearn/utils/datasets.py
tklearn/utils/download.py
textkit_learn-0.3.9.dist-info/METADATA
textkit_learn-0.3.9.dist-info/WHEEL
textkit_learn-0.3.9.dist-info/licenses/LICENSE
textkit_learn-0.3.9.dist-info/RECORD
