Metadata-Version: 2.1
Name: textkit-learn
Version: 0.3.9
Summary: Helps computers to understand human languages.
Project-URL: Homepage, https://github.com/ysenarath/textkit-learn
Project-URL: Repository, https://github.com/ysenarath/textkit-learn
Project-URL: Issues, https://github.com/ysenarath/textkit-learn/issues
Project-URL: Changelog, https://github.com/ysenarath/textkit-learn/blob/master/CHANGELOG.md
Author: Yasas Senarath
License-Expression: MIT
License-File: LICENSE
Classifier: Development Status :: 4 - Beta
Classifier: Intended Audience :: Developers
Classifier: License :: OSI Approved :: MIT License
Classifier: Operating System :: MacOS
Classifier: Operating System :: Microsoft :: Windows
Classifier: Operating System :: POSIX :: Linux
Classifier: Programming Language :: Python
Classifier: Programming Language :: Python :: 3
Classifier: Programming Language :: Python :: 3.8
Classifier: Programming Language :: Python :: 3.9
Classifier: Programming Language :: Python :: 3.10
Classifier: Programming Language :: Python :: 3.11
Classifier: Programming Language :: Python :: 3.12
Classifier: Programming Language :: Python :: 3.13
Classifier: Programming Language :: Rust
Classifier: Typing :: Typed
Requires-Python: >=3.8
Requires-Dist: accelerate
Requires-Dist: datasets
Requires-Dist: evaluate
Requires-Dist: flashtext
Requires-Dist: hnswlib
Requires-Dist: langdetect
Requires-Dist: nltk
Requires-Dist: numpy
Requires-Dist: pandas
Requires-Dist: polars
Requires-Dist: pyarrow
Requires-Dist: scikit-learn!=1.3,>=1.4.0
Requires-Dist: sortedcontainers
Requires-Dist: torch
Requires-Dist: transformers
Requires-Dist: werkzeug
